radtorch/__init__.py
radtorch/datautils.py
radtorch/dicomutils.py
radtorch/generalutils.py
radtorch/modelsutils.py
radtorch/pipeline.py
radtorch/visutils.py
radtorch-0.1.2.dist-info/LICENSE
radtorch-0.1.2.dist-info/METADATA
radtorch-0.1.2.dist-info/WHEEL
radtorch-0.1.2.dist-info/top_level.txt
radtorch-0.1.2.dist-info/RECORD
